{
  "name": "Ethel Figueroa",
  "age": 29,
  "address": {
    "street": "Orboh Boulevard",
    "city": "Wofcooc",
    "state": "ND",
    "zip": "59007"
  },
  "contact": {
    "phone": "(644) 962-8180",
    "servicePhone": "800136377"
  },
  "birthday": "1987-01-28T02:20:18.171Z",
  "ip": "190.60.221.63",
  "foo": "bar",
  "profile": {
    "about": "Nekuf mipon vabuwi ewujumco zetcaowi ru dogo gafkir puheha lipadeve seojo gu igaihuzan ufe. Mesuwab vedgi sosuv sopwad risarno beg ni domi verku rurejiw uf mij eje. Jo sor hesi gik hacuso oj getebal cezigujeb ranwaw cavi okezosa ca fetojih mezzi. Ezaocof hezpud roze nezefzag ogpodad nizucur heloc orsaw bemak jipog apepana par mofe. Hu seghosoh cetu pa rad fari hise gevsel dah rafkeir ivo wa vaf.",
    "bio": "Ah housawu dapub wo ocipalme gu rikga jeclup lu zema liwnikpo mojofvum ib catno telad teibuece. Peeltem ro wigawga lece ujiti jo sevomlu vekpe rupod ga cacifutu dizfuwoz ci acuutuce zezika. Ju lugged efiwis be sewavjun ta fersa ni hocfi sa egzowak sewo rujlucwiv enefaksew cot uwcukoc. Pohza amaguto osa mifoif pi bapos kumu peklu vaufe rup nidgomik nibop oc saf talcectoc lono firmimviw."
  },
  "apiKey": "1eec7850d9f155951c27ab9dec88b7781d1296950d55b62e3181af79836d3fe6",
  "currency": {
    "code": "MDL",
    "name": "Moldova Leu"
  }
}