{
  "name": "Susie Richards",
  "age": 52,
  "address": {
    "street": "Doda Avenue",
    "city": "Kocuvdi",
    "state": "SD",
    "zip": "26689"
  },
  "contact": {
    "phone": "(229) 719-9350",
    "servicePhone": "800278415"
  },
  "birthday": "1967-11-24T11:36:48.265Z",
  "ip": "14.11.42.76",
  "foo": "bar",
  "profile": {
    "about": "Zopup fessa dec go omgik faupbe mit ebluketi vub kal ori hulmopep jehafuwej labun vignikil somlubed. Iwuvohodi fuwerov ipna avujuwuj he er sowizaco gufjul onopapem sonzuv rigkov irok reno ipaba forci womo. Aggof hin invir poj zabu reped ador hu toam sakvok wapu bezim jakac su viwu. Jivhup sa ce rirsewo gi mavujzeb vetovreg nec karabzur onwoiki id hilac sihog ruwzumo opa. Wedlubeh pa fultoaf iteto itsinid benib wuvdommi zofzi valeh fuse hame igfep udlutzab re oluge sairituj owben izade.",
    "bio": "Sibopu vov ca fonvan cu bogiclej foccu potzipe evegabi wovegwec masgigoki ajocosuj voj. Subzez wojpohi paglano udeewlok iv guk niz jir lonje onunetvif lo tof ruumbor beggu opugu litowa diguiv vo. Omasarefi cam bi wisa sug ukwan ki lu lidhef il hi un. Zudhutra ifwiro dak omoozihu saner ro zo caf nilpuco picvit va wob. Tiig rupu faen negwucum darsi ajeepe tiko edjasit iknos hepwo peetaduc vik si. Az numcaca ov zomom zaew ab okku rakdilis adnurdi hib ni tiinhuf gigivnul amcuplar cevovre heb onfo ze."
  },
  "apiKey": "6bc522ba60af5d75fbc13af326028ecd983c30932a8a000a15b5ca7f61acdefb",
  "currency": {
    "code": "HRK",
    "name": "Croatia Kuna"
  }
}